AsyncGraphqlZhongwenWendangFix1/README.md
AsyncGraphqlZhongwenWendangFix1/__init__.py
AsyncGraphqlZhongwenWendangFix1/__main__.py
AsyncGraphqlZhongwenWendangFix1/file.epub
AsyncGraphqlZhongwenWendangFix1/index.html
AsyncGraphqlZhongwenWendangFix1/css/__init__.py
AsyncGraphqlZhongwenWendangFix1/css/annotations.css
AsyncGraphqlZhongwenWendangFix1/css/main.css
AsyncGraphqlZhongwenWendangFix1/css/normalize.css
AsyncGraphqlZhongwenWendangFix1/css/popup.css
AsyncGraphqlZhongwenWendangFix1/font/__init__.py
AsyncGraphqlZhongwenWendangFix1/font/fontello.eot
AsyncGraphqlZhongwenWendangFix1/font/fontello.svg
AsyncGraphqlZhongwenWendangFix1/font/fontello.ttf
AsyncGraphqlZhongwenWendangFix1/font/fontello.woff
AsyncGraphqlZhongwenWendangFix1/img/__init__.py
AsyncGraphqlZhongwenWendangFix1/img/annotator-glyph-sprite.png
AsyncGraphqlZhongwenWendangFix1/img/annotator-icon-sprite.png
AsyncGraphqlZhongwenWendangFix1/img/apple-touch-icon.png
AsyncGraphqlZhongwenWendangFix1/img/cancelfullscreen.png
AsyncGraphqlZhongwenWendangFix1/img/close.png
AsyncGraphqlZhongwenWendangFix1/img/fullscreen.png
AsyncGraphqlZhongwenWendangFix1/img/loader.gif
AsyncGraphqlZhongwenWendangFix1/img/menu-icon.png
AsyncGraphqlZhongwenWendangFix1/img/save.png
AsyncGraphqlZhongwenWendangFix1/img/saved.png
AsyncGraphqlZhongwenWendangFix1/img/settings-s.png
AsyncGraphqlZhongwenWendangFix1/img/settings.png
AsyncGraphqlZhongwenWendangFix1/img/star.png
AsyncGraphqlZhongwenWendangFix1/js/__init__.py
AsyncGraphqlZhongwenWendangFix1/js/epub.js
AsyncGraphqlZhongwenWendangFix1/js/epub.min.js
AsyncGraphqlZhongwenWendangFix1/js/epub.min.map
AsyncGraphqlZhongwenWendangFix1/js/hooks.min.js
AsyncGraphqlZhongwenWendangFix1/js/hooks.min.map
AsyncGraphqlZhongwenWendangFix1/js/reader.js
AsyncGraphqlZhongwenWendangFix1/js/reader.js.map
AsyncGraphqlZhongwenWendangFix1/js/reader.min.js
AsyncGraphqlZhongwenWendangFix1/js/reader.min.map
AsyncGraphqlZhongwenWendangFix1/js/hooks/__init__.py
async_graphql_zhongwen_wendang_fix1-2025.3.25.0.dist-info/METADATA
async_graphql_zhongwen_wendang_fix1-2025.3.25.0.dist-info/WHEEL
async_graphql_zhongwen_wendang_fix1-2025.3.25.0.dist-info/entry_points.txt
async_graphql_zhongwen_wendang_fix1-2025.3.25.0.dist-info/top_level.txt
async_graphql_zhongwen_wendang_fix1-2025.3.25.0.dist-info/RECORD
